crudgen/__init__.py
crudgen/apps.py
crudgen/generators.py
django_crudgen-0.1.0.dist-info/METADATA
django_crudgen-0.1.0.dist-info/WHEEL
django_crudgen-0.1.0.dist-info/top_level.txt
django_crudgen-0.1.0.dist-info/RECORD
