Metadata-Version: 2.1
Name: django-crudgen
Version: 0.1.0
Summary: A simple package to generate CRUD views for Django models.
Home-page: https://github.com/mohammadkhoddami/django-crudgen
Author: Mohammad Hasan Khoddami
Author-email: mohammadh.khoddami@gmail.com
License: MIT
Classifier: Programming Language :: Python :: 3
Classifier: Framework :: Django
Classifier: License :: OSI Approved :: MIT License
Classifier: Operating System :: OS Independent
Requires-Python: >=3.6
Requires-Dist: django>=3.0
